compose4py/__init__.py
compose4py/misc.py
compose4py-1.3.3.dist-info/LICENSE
compose4py-1.3.3.dist-info/METADATA
compose4py-1.3.3.dist-info/WHEEL
compose4py-1.3.3.dist-info/top_level.txt
compose4py-1.3.3.dist-info/RECORD
