Metadata-Version: 2.1
Name: compose4py
Version: 1.3.3
Summary: Onion Model in Python
Home-page: https://github.com/chatopera/compose4py
Author: Hai Liang Wang
Author-email: hain@chatopera.com
License: Apache Software License
Keywords: onion,compose,chain
Platform: UNKNOWN
Classifier: Intended Audience :: Developers
Classifier: License :: OSI Approved :: Apache Software License
Classifier: Operating System :: OS Independent
Classifier: Natural Language :: Chinese (Simplified)
Classifier: Natural Language :: Chinese (Traditional)
Classifier: Programming Language :: Python
Classifier: Programming Language :: Python :: 3
Classifier: Topic :: Utilities
